plusnethubtwo/__init__.py
plusnethubtwo/plusnethubtwo.py
plusnethubtwo-0.0.4.dist-info/METADATA
plusnethubtwo-0.0.4.dist-info/WHEEL
plusnethubtwo-0.0.4.dist-info/licenses/LICENSE
plusnethubtwo-0.0.4.dist-info/RECORD
