Metadata-Version: 2.4
Name: plusnethubtwo
Version: 0.0.4
Summary: A Python Package that can control and fetch data from the Plusnet Hub Two router
Author: Max Blagg
License-Expression: MIT
License-File: LICENSE
Classifier: Operating System :: OS Independent
Classifier: Programming Language :: Python :: 3
Requires-Python: >=3.8
